ekosisteem/__init__.py
ekosisteem-0.0.0.dist-info/METADATA
ekosisteem-0.0.0.dist-info/WHEEL
ekosisteem-0.0.0.dist-info/top_level.txt
ekosisteem-0.0.0.dist-info/RECORD
