Metadata-Version: 2.1
Name: ekosisteem
Version: 0.0.0
Summary: Coming soon
Author-email: Dirk Botha <bothadj@gmail.com>
